catweazle/__init__.py
catweazle/config.py
catweazle/errors.py
catweazle/main.py
catweazle/authorize/__init__.py
catweazle/controller/__init__.py
catweazle/controller/api/__init__.py
catweazle/controller/api/v1/__init__.py
catweazle/controller/api/v1/instances.py
catweazle/controller/api/v2/__init__.py
catweazle/controller/api/v2/authenticate.py
catweazle/controller/api/v2/instances.py
catweazle/controller/api/v2/permissions.py
catweazle/controller/api/v2/users.py
catweazle/controller/api/v2/users_credentials.py
catweazle/controller/oauth/__init__.py
catweazle/controller/oauth/authenticate.py
catweazle/crud/__init__.py
catweazle/crud/common.py
catweazle/crud/credentials.py
catweazle/crud/foreman.py
catweazle/crud/instances.py
catweazle/crud/ldap.py
catweazle/crud/mixins.py
catweazle/crud/oauth.py
catweazle/crud/permissions.py
catweazle/crud/users.py
catweazle/model/__init__.py
catweazle/model/oauth.py
catweazle/model/v1/__init__.py
catweazle/model/v1/instances.py
catweazle/model/v2/__init__.py
catweazle/model/v2/authenticate.py
catweazle/model/v2/common.py
catweazle/model/v2/credentials.py
catweazle/model/v2/instances.py
catweazle/model/v2/permissions.py
catweazle/model/v2/users.py
catweazle-1.0.6.dist-info/METADATA
catweazle-1.0.6.dist-info/WHEEL
catweazle-1.0.6.dist-info/entry_points.txt
catweazle-1.0.6.dist-info/licenses/LICENSE.txt
catweazle-1.0.6.dist-info/RECORD
