Metadata-Version: 2.4
Name: catweazle
Version: 1.0.6
Summary: catweazle, dynamic DNS and Redhat IdM/FreeIPA registration system
Author-email: "Stephan.Schultchen" <stephan.schultchen@gmail.com>
License:                     GNU AFFERO GENERAL PUBLIC LICENSE
License-File: LICENSE.txt
Classifier: Programming Language :: Python
Requires-Python: >=3.9
Requires-Dist: annotated-doc==0.0.3
Requires-Dist: annotated-types==0.7.0
Requires-Dist: anyio==4.11.0
Requires-Dist: authlib==1.6.6
Requires-Dist: bonsai==1.5.4
Requires-Dist: certifi==2025.10.5
Requires-Dist: cffi==2.0.0
Requires-Dist: click==8.3.0
Requires-Dist: cryptography==46.0.3
Requires-Dist: dnspython==2.8.0
Requires-Dist: email-validator==2.3.0
Requires-Dist: fastapi-cli==0.0.14
Requires-Dist: fastapi-cloud-cli==0.3.1
Requires-Dist: fastapi==0.120.1
Requires-Dist: h11==0.16.0
Requires-Dist: httpcore==1.0.9
Requires-Dist: httptools==0.7.1
Requires-Dist: httpx==0.28.1
Requires-Dist: idna==3.11
Requires-Dist: itsdangerous==2.2.0
Requires-Dist: jinja2==3.1.6
Requires-Dist: markdown-it-py==4.0.0
Requires-Dist: markupsafe==3.0.3
Requires-Dist: mdurl==0.1.2
Requires-Dist: motor==3.7.1
Requires-Dist: passlib==1.7.4
Requires-Dist: pycparser==2.23
Requires-Dist: pydantic-core==2.41.4
Requires-Dist: pydantic-settings==2.11.0
Requires-Dist: pydantic==2.12.3
Requires-Dist: pygments==2.19.2
Requires-Dist: pymongo==4.15.3
Requires-Dist: python-dotenv==1.2.1
Requires-Dist: python-multipart==0.0.20
Requires-Dist: pyyaml==6.0.3
Requires-Dist: rich-toolkit==0.15.1
Requires-Dist: rich==14.2.0
Requires-Dist: rignore==0.7.1
Requires-Dist: sentry-sdk==2.42.1
Requires-Dist: shellingham==1.5.4
Requires-Dist: sniffio==1.3.1
Requires-Dist: starlette==0.49.1
Requires-Dist: typer==0.20.0
Requires-Dist: typing-extensions==4.15.0
Requires-Dist: typing-inspection==0.4.2
Requires-Dist: urllib3==2.6.3
Requires-Dist: uvicorn==0.38.0
Requires-Dist: uvloop==0.22.1
Requires-Dist: watchfiles==1.1.1
Requires-Dist: websockets==15.0.1
